LICENSE
README.md
setup.py
autogan/__init__.py
autogan/agents/__init__.py
autogan/agents/agent_switch.py
autogan/agents/human_agent.py
autogan/agents/tool_agent_code_execution.py
autogan/agents/tool_agent_file_append.py
autogan/agents/tool_agent_file_read.py
autogan/agents/tool_agent_mail.py
autogan/agents/tool_agent_web_search.py
autogan/agents/tool_agent_wolfram_alpha.py
autogan/agents/universal_agent.py
autogan/oai/__init__.py
autogan/oai/config_utils.py
autogan/oai/count_tokens_utils.py
autogan/oai/generate_utils.py
autogan/oai/openai_utils.py
autogan/utils/__init__.py
autogan/utils/compressed_messages_utils.py
autogan/utils/compressed_text_utils.py
autogan/utils/environment_utils.py
autogan/utils/json_utils.py
autogan/utils/response.py
pyautogan.egg-info/PKG-INFO
pyautogan.egg-info/SOURCES.txt
pyautogan.egg-info/dependency_links.txt
pyautogan.egg-info/requires.txt
pyautogan.egg-info/top_level.txt