Metadata-Version: 2.1
Name: pyautogan
Version: 0.1
Summary: AutoGenius is an agent framework.
Home-page: UNKNOWN
Author: boweniac
Author-email: boweniac@yeah.net
License: UNKNOWN
Keywords: python,chatgpt,agent
Platform: UNKNOWN
Classifier: Development Status :: 3 - Alpha
Classifier: Intended Audience :: Developers
Classifier: Programming Language :: Python :: 3.8
Classifier: Operating System :: Unix
Classifier: Operating System :: MacOS :: MacOS X
License-File: LICENSE
